pretix_oidc/__init__.py
pretix_oidc/auth.py
pretix_oidc/signals.py
pretix_oidc/urls.py
pretix_oidc/utils.py
pretix_oidc/views.py
pretix_oidc/locale/de/LC_MESSAGES/django.mo
pretix_oidc/locale/de/LC_MESSAGES/django.po
pretix_oidc/locale/de_Informal/.gitkeep
pretix_oidc/locale/de_Informal/LC_MESSAGES/django.mo
pretix_oidc/locale/de_Informal/LC_MESSAGES/django.po
pretix_oidc/management/__init__.py
pretix_oidc/management/commands/__init__.py
pretix_oidc/management/commands/dumpdata_unscoped.py
pretix_oidc/static/pretix_oidc/.gitkeep
pretix_oidc/templates/pretix_oidc/.gitkeep
pretix_keycloak_oidc-1.1.0.dist-info/LICENSE
pretix_keycloak_oidc-1.1.0.dist-info/METADATA
pretix_keycloak_oidc-1.1.0.dist-info/WHEEL
pretix_keycloak_oidc-1.1.0.dist-info/entry_points.txt
pretix_keycloak_oidc-1.1.0.dist-info/top_level.txt
pretix_keycloak_oidc-1.1.0.dist-info/RECORD
