Metadata-Version: 2.1
Name: pretix-keycloak-oidc
Version: 1.1.0
Summary: This is a plugin for pretix that provides a pluggable OIDC authentication backend for keycloak servers.
Home-page: https://github.com/adevolutio/pretix-oidc
Author: Evolutio
Author-email: jpolonia@evolutio.pt
License: Apache
Platform: UNKNOWN
License-File: LICENSE
Requires-Dist: josepy
